banxico/__init__.py
banxico/_indicadores.py
data_format/__init__.py
data_format/_auxiliar.py
inegi/__init__.py
inegi/_banco_de_indicadores.py
datos_mx-1.0.dist-info/LICENSE.md
datos_mx-1.0.dist-info/METADATA
datos_mx-1.0.dist-info/WHEEL
datos_mx-1.0.dist-info/top_level.txt
datos_mx-1.0.dist-info/RECORD
